pypas/__init__.py
pypas/central_credential_provider.py
pypas/hello.py
pypas/utils.py
pypas/vault.py
pypas/api/authentication_api.py
pypas/api/central_credential_provider_api.py
pypas/api/safe_api.py
pypas/model/application.py
pypas/model/applicaton_authentication_method.py
pypas/model/credential.py
pypas/model/group.py
pypas/model/reqresuser.py
pypas/model/safe.py
pypas/model/safe_member.py
pypas/model/user.py
pypas-0.0.2rc28.post1.dist-info/LICENSE
pypas-0.0.2rc28.post1.dist-info/WHEEL
pypas-0.0.2rc28.post1.dist-info/METADATA
pypas-0.0.2rc28.post1.dist-info/RECORD
